vector_classifier/__init__.py
vector_classifier/classifier.py
vector_classifier/examples_imports.py
vector_classifier/types.py
vector_classifier/embed/hf_provider.py
vector_classifier/embed/openai_provider.py
vector_classifier/embed/provider.py
vector_classifier/examples/__init__.py
vector_classifier/examples/ai_sdk_search.py
vector_classifier/preprocess/text.py
vector_classifier/rag/__init__.py
vector_classifier/rag/chunk.py
vector_classifier/rag/client.py
vector_classifier/rag/fetchers.py
vector_classifier/rag/index.py
vector_classifier/rag/registry.py
vector_classifier/rag/tools.py
vector_classifier/utils/cost.py
vector_classifier/utils/logger.py
vector_classifier/utils/retry.py
vector_classifier/utils/vote.py
vector_classifier/vector/pinecone_store.py
vector_classifier/vector/store.py
vector_classifier_python-0.1.1.dist-info/METADATA
vector_classifier_python-0.1.1.dist-info/WHEEL
vector_classifier_python-0.1.1.dist-info/RECORD
