Metadata-Version: 2.4
Name: vector-classifier-python
Version: 0.1.1
Summary: Retrieval-based classification for structured data using embeddings and Pinecone. Zero-training, fast to integrate.
Project-URL: Homepage, https://github.com/
Project-URL: Repository, https://github.com/
Author: Scout
License: MIT
Requires-Python: >=3.9
Requires-Dist: beautifulsoup4>=4.12.0
Requires-Dist: gitpython>=3.1.43
Requires-Dist: huggingface-hub>=0.23.0
Requires-Dist: markdownify>=0.13.1
Requires-Dist: openai>=1.30.0
Requires-Dist: pinecone>=5.0.0
Requires-Dist: playwright>=1.45.0; sys_platform != 'win32' or platform_system == 'Windows'
Requires-Dist: requests>=2.31.0
Requires-Dist: typing-extensions>=4.8.0
